quick_convert/__init__.py
quick_convert/convert.py
quick_convert-0.1.3.dist-info/METADATA
quick_convert-0.1.3.dist-info/WHEEL
quick_convert-0.1.3.dist-info/entry_points.txt
quick_convert-0.1.3.dist-info/RECORD
